smplr/__init__.py
smplr/_version.py
smplr/_version.pyi
smplr/py.typed
smplr-0.0.2.dist-info/METADATA
smplr-0.0.2.dist-info/WHEEL
smplr-0.0.2.dist-info/licenses/LICENSE
smplr-0.0.2.dist-info/RECORD
