Metadata-Version: 2.4
Name: smplr
Version: 0.0.2
Summary: Simplified smpl
Project-URL: Homepage, https://github.com/APN-Pucky/smplr
Project-URL: Bug Tracker, https://github.com/APN-Pucky/smplr/issues
Project-URL: Discussions, https://github.com/APN-Pucky/smplr/discussions
Project-URL: Changelog, https://github.com/APN-Pucky/smplr/releases
Author-email: Alexander Puck Neuwirth <alexander@neuwirth-informatik.de>
License-Expression: BSD-3-Clause
License-File: LICENSE
Classifier: Development Status :: 1 - Planning
Classifier: Intended Audience :: Developers
Classifier: Intended Audience :: Science/Research
Classifier: Operating System :: OS Independent
Classifier: Programming Language :: Python
Classifier: Programming Language :: Python :: 3
Classifier: Programming Language :: Python :: 3 :: Only
Classifier: Programming Language :: Python :: 3.9
Classifier: Programming Language :: Python :: 3.10
Classifier: Programming Language :: Python :: 3.11
Classifier: Programming Language :: Python :: 3.12
Classifier: Programming Language :: Python :: 3.13
Classifier: Topic :: Scientific/Engineering
Classifier: Typing :: Typed
Requires-Python: >=3.9
Requires-Dist: matplotlib
